gym_rock_paper_scissors/__init__.py
gym_rock_paper_scissors/envs/__init__.py
gym_rock_paper_scissors/envs/one_hot_space.py
gym_rock_paper_scissors/envs/rock_paper_scissors_env.py
gym_rock_paper_scissors/envs/tests/__init__.py
gym_rock_paper_scissors/envs/tests/external_env_variables_mutability_test.py
gym_rock_paper_scissors/envs/tests/state_space_size.py
gym_rock_paper_scissors/fixed_agents/__init__.py
gym_rock_paper_scissors/fixed_agents/mixed_strategy_agent.py
gym_rock_paper_scissors-0.1.dist-info/METADATA
gym_rock_paper_scissors-0.1.dist-info/RECORD
gym_rock_paper_scissors-0.1.dist-info/WHEEL
gym_rock_paper_scissors-0.1.dist-info/top_level.txt
