Metadata-Version: 2.1
Name: gym-rock-paper-scissors
Version: 0.1
Summary: OpenAI gym environment for a repeated game of Rock-Paper-Scissors
Home-page: https://github.com/Danielhp95/gym-rock-paper-scissors
Author: Sarios
Author-email: rockpapersass@xcape.com
License: UNKNOWN
Platform: UNKNOWN
Requires-Dist: gym
